.DS_Store
CowMQ-0.1.3.dist-info/DESCRIPTION.rst
CowMQ-0.1.3.dist-info/METADATA
CowMQ-0.1.3.dist-info/RECORD
CowMQ-0.1.3.dist-info/WHEEL
CowMQ-0.1.3.dist-info/metadata.json
CowMQ-0.1.3.dist-info/top_level.txt
cow_mq/__init__.py
cow_mq/blueprint.py
cow_mq/client.py
cow_mq/server.py
cow_mq/util.py
